[
    {
        "erc1155":[],
        "erc20":{
            "amounts":[
                "1000000000000"
            ],
            "contractAddresses":[
                "0x7399Ea6C9d35124d893B8d9808930e9d3F211501"
            ]
        },
        "erc721":[],
        "to":"0x2DCD241135d2d5b2E9bA2926e436c054FDF8BF0B"
    },
    {
        "erc1155":[],
        "erc20":{
            "amounts":[
                "800000000000"
            ],
            "contractAddresses":[
                "0x7399Ea6C9d35124d893B8d9808930e9d3F211501"
            ]
        },
        "erc721":[],
        "to":"0x7D0CAeFbe8a6F66AeA68389f8cbff9052ACd8fd7"
    },
    {
        "erc1155":[],
        "erc20":{
            "amounts":[
                "800000000000"
            ],
            "contractAddresses":[
                "0x7399Ea6C9d35124d893B8d9808930e9d3F211501"
            ]
        },
        "erc721":[],
        "to":"0x75d56B0103ea3b596D344e153CC89012aF3bD22A"
    }
]
